{
  "code": 0,
  "msg": "success",
  "time": "1778067922",
  "data": {
    "outdoor": {
      "temperature": {
        "time": "1778067900",
        "unit": "℃",
        "value": "19.8"
      },
      "feels_like": {
        "time": "1778067900",
        "unit": "℃",
        "value": "19.8"
      },
      "app_temp": {
        "time": "1778067900",
        "unit": "℃",
        "value": "21.6"
      },
      "dew_point": {
        "time": "1778067900",
        "unit": "℃",
        "value": "18.9"
      },
      "humidity": {
        "time": "1778067900",
        "unit": "%",
        "value": "95"
      }
    },
    "solar_and_uvi": {
      "solar": {
        "time": "1778067900",
        "unit": "W/m²",
        "value": "73.7"
      },
      "uvi": {
        "time": "1778067900",
        "unit": "",
        "value": "0"
      }
    },
    "rainfall": {
      "rain_rate": {
        "time": "1778067900",
        "unit": "mm/hr",
        "value": 0
      },
      "daily": {
        "time": "1778067900",
        "unit": "mm",
        "value": 0
      },
      "event": {
        "time": "1778067900",
        "unit": "mm",
        "value": 0
      },
      "1_hour": {
        "time": "1778067900",
        "unit": "mm",
        "value": 0
      },
      "weekly": {
        "time": "1778067900",
        "unit": "mm",
        "value": 0
      },
      "monthly": {
        "time": "1778067900",
        "unit": "mm",
        "value": 0
      },
      "yearly": {
        "time": "1778067900",
        "unit": "mm",
        "value": 100.1
      }
    },
    "wind": {
      "wind_speed": {
        "time": "1778067900",
        "unit": "km/h",
        "value": "7.2"
      },
      "wind_gust": {
        "time": "1778067900",
        "unit": "km/h",
        "value": "11.2"
      },
      "wind_direction": {
        "time": "1778067900",
        "unit": "º",
        "value": "53"
      }
    },
    "pressure": {
      "relative": {
        "time": "1778067900",
        "unit": "hPa",
        "value": "1005.8"
      },
      "absolute": {
        "time": "1778067900",
        "unit": "hPa",
        "value": "1000.7"
      }
    }
  }
}
