{
  "code": 0,
  "msg": "success",
  "time": "1775580153",
  "data": {
    "outdoor": {
      "temperature": {
        "time": "1775580148",
        "unit": "℃",
        "value": "18.7"
      },
      "feels_like": {
        "time": "1775580148",
        "unit": "℃",
        "value": "18.7"
      },
      "app_temp": {
        "time": "1775580148",
        "unit": "℃",
        "value": "18.0"
      },
      "dew_point": {
        "time": "1775580148",
        "unit": "℃",
        "value": "15.9"
      },
      "humidity": {
        "time": "1775580148",
        "unit": "%",
        "value": "84"
      }
    },
    "solar_and_uvi": {
      "solar": {
        "time": "1775580148",
        "unit": "W/m²",
        "value": "259.8"
      },
      "uvi": {
        "time": "1775580148",
        "unit": "",
        "value": "2"
      }
    },
    "rainfall": {
      "rain_rate": {
        "time": "1775580148",
        "unit": "mm/hr",
        "value": 0
      },
      "daily": {
        "time": "1775580148",
        "unit": "mm",
        "value": 1.3
      },
      "event": {
        "time": "1775580148",
        "unit": "mm",
        "value": 27.2
      },
      "1_hour": {
        "time": "1775580148",
        "unit": "mm",
        "value": 0
      },
      "weekly": {
        "time": "1775580148",
        "unit": "mm",
        "value": 27.2
      },
      "monthly": {
        "time": "1775580148",
        "unit": "mm",
        "value": 67.8
      },
      "yearly": {
        "time": "1775580148",
        "unit": "mm",
        "value": 77.2
      }
    },
    "wind": {
      "wind_speed": {
        "time": "1775580148",
        "unit": "km/h",
        "value": "13.7"
      },
      "wind_gust": {
        "time": "1775580148",
        "unit": "km/h",
        "value": "16.6"
      },
      "wind_direction": {
        "time": "1775580148",
        "unit": "º",
        "value": "187"
      }
    },
    "pressure": {
      "relative": {
        "time": "1775580148",
        "unit": "hPa",
        "value": "1010.9"
      },
      "absolute": {
        "time": "1775580148",
        "unit": "hPa",
        "value": "1005.8"
      }
    }
  }
}
