{
  "code": 0,
  "msg": "success",
  "time": "1777128917",
  "data": {
    "outdoor": {
      "temperature": {
        "time": "1777128872",
        "unit": "℃",
        "value": "22.1"
      },
      "feels_like": {
        "time": "1777128872",
        "unit": "℃",
        "value": "22.1"
      },
      "app_temp": {
        "time": "1777128872",
        "unit": "℃",
        "value": "19.8"
      },
      "dew_point": {
        "time": "1777128872",
        "unit": "℃",
        "value": "8.9"
      },
      "humidity": {
        "time": "1777128872",
        "unit": "%",
        "value": "43"
      }
    },
    "solar_and_uvi": {
      "solar": {
        "time": "1777128872",
        "unit": "W/m²",
        "value": "359.1"
      },
      "uvi": {
        "time": "1777128872",
        "unit": "",
        "value": "3"
      }
    },
    "rainfall": {
      "rain_rate": {
        "time": "1777128872",
        "unit": "mm/hr",
        "value": 0
      },
      "daily": {
        "time": "1777128872",
        "unit": "mm",
        "value": 0
      },
      "event": {
        "time": "1777128872",
        "unit": "mm",
        "value": 0
      },
      "1_hour": {
        "time": "1777128872",
        "unit": "mm",
        "value": 0
      },
      "weekly": {
        "time": "1777128872",
        "unit": "mm",
        "value": 22.9
      },
      "monthly": {
        "time": "1777128872",
        "unit": "mm",
        "value": 90.7
      },
      "yearly": {
        "time": "1777128872",
        "unit": "mm",
        "value": 100.1
      }
    },
    "wind": {
      "wind_speed": {
        "time": "1777128872",
        "unit": "km/h",
        "value": "10.8"
      },
      "wind_gust": {
        "time": "1777128872",
        "unit": "km/h",
        "value": "11.2"
      },
      "wind_direction": {
        "time": "1777128872",
        "unit": "º",
        "value": "230"
      }
    },
    "pressure": {
      "relative": {
        "time": "1777128872",
        "unit": "hPa",
        "value": "1012.5"
      },
      "absolute": {
        "time": "1777128872",
        "unit": "hPa",
        "value": "1007.4"
      }
    }
  }
}
