{
  "code": 0,
  "msg": "success",
  "time": "1783607461",
  "data": {
    "outdoor": {
      "temperature": {
        "time": "1783607436",
        "unit": "℃",
        "value": "14.4"
      },
      "feels_like": {
        "time": "1783607436",
        "unit": "℃",
        "value": "14.4"
      },
      "app_temp": {
        "time": "1783607436",
        "unit": "℃",
        "value": "13.5"
      },
      "dew_point": {
        "time": "1783607436",
        "unit": "℃",
        "value": "8.8"
      },
      "humidity": {
        "time": "1783607436",
        "unit": "%",
        "value": "69"
      }
    },
    "solar_and_uvi": {
      "solar": {
        "time": "1783607436",
        "unit": "W/m²",
        "value": "320.6"
      },
      "uvi": {
        "time": "1783607436",
        "unit": "",
        "value": "3"
      }
    },
    "rainfall": {
      "rain_rate": {
        "time": "1783607436",
        "unit": "mm/hr",
        "value": 0
      },
      "daily": {
        "time": "1783607436",
        "unit": "mm",
        "value": 0
      },
      "event": {
        "time": "1783607436",
        "unit": "mm",
        "value": 0
      },
      "1_hour": {
        "time": "1783607436",
        "unit": "mm",
        "value": 0
      },
      "weekly": {
        "time": "1783607436",
        "unit": "mm",
        "value": 7.9
      },
      "monthly": {
        "time": "1783607436",
        "unit": "mm",
        "value": 7.9
      },
      "yearly": {
        "time": "1783607436",
        "unit": "mm",
        "value": 167.4
      }
    },
    "wind": {
      "wind_speed": {
        "time": "1783607436",
        "unit": "km/h",
        "value": "3.2"
      },
      "wind_gust": {
        "time": "1783607436",
        "unit": "km/h",
        "value": "3.6"
      },
      "wind_direction": {
        "time": "1783607436",
        "unit": "º",
        "value": "328"
      }
    },
    "pressure": {
      "relative": {
        "time": "1783607436",
        "unit": "hPa",
        "value": "1013.8"
      },
      "absolute": {
        "time": "1783607436",
        "unit": "hPa",
        "value": "1008.7"
      }
    }
  }
}
