{
  "code": 0,
  "msg": "success",
  "time": "1776788124",
  "data": {
    "outdoor": {
      "temperature": {
        "time": "1776788113",
        "unit": "℃",
        "value": "16.8"
      },
      "feels_like": {
        "time": "1776788113",
        "unit": "℃",
        "value": "16.8"
      },
      "app_temp": {
        "time": "1776788113",
        "unit": "℃",
        "value": "16.4"
      },
      "dew_point": {
        "time": "1776788113",
        "unit": "℃",
        "value": "15.8"
      },
      "humidity": {
        "time": "1776788113",
        "unit": "%",
        "value": "94"
      }
    },
    "solar_and_uvi": {
      "solar": {
        "time": "1776788113",
        "unit": "W/m²",
        "value": "74.3"
      },
      "uvi": {
        "time": "1776788113",
        "unit": "",
        "value": "0"
      }
    },
    "rainfall": {
      "rain_rate": {
        "time": "1776788113",
        "unit": "mm/hr",
        "value": 6.1
      },
      "daily": {
        "time": "1776788113",
        "unit": "mm",
        "value": 11.7
      },
      "event": {
        "time": "1776788113",
        "unit": "mm",
        "value": 22.4
      },
      "1_hour": {
        "time": "1776788113",
        "unit": "mm",
        "value": 1.5
      },
      "weekly": {
        "time": "1776788113",
        "unit": "mm",
        "value": 22.4
      },
      "monthly": {
        "time": "1776788113",
        "unit": "mm",
        "value": 90.2
      },
      "yearly": {
        "time": "1776788113",
        "unit": "mm",
        "value": 99.6
      }
    },
    "wind": {
      "wind_speed": {
        "time": "1776788113",
        "unit": "km/h",
        "value": "11.9"
      },
      "wind_gust": {
        "time": "1776788113",
        "unit": "km/h",
        "value": "16.6"
      },
      "wind_direction": {
        "time": "1776788113",
        "unit": "º",
        "value": "280"
      }
    },
    "pressure": {
      "relative": {
        "time": "1776788113",
        "unit": "hPa",
        "value": "1012.7"
      },
      "absolute": {
        "time": "1776788113",
        "unit": "hPa",
        "value": "1007.6"
      }
    }
  }
}
