{
  "code": 0,
  "msg": "success",
  "time": "1778970021",
  "data": {
    "outdoor": {
      "temperature": {
        "time": "1778970016",
        "unit": "℃",
        "value": "10.9"
      },
      "feels_like": {
        "time": "1778970016",
        "unit": "℃",
        "value": "10.9"
      },
      "app_temp": {
        "time": "1778970016",
        "unit": "℃",
        "value": "8.3"
      },
      "dew_point": {
        "time": "1778970016",
        "unit": "℃",
        "value": "9.9"
      },
      "humidity": {
        "time": "1778970016",
        "unit": "%",
        "value": "94"
      }
    },
    "solar_and_uvi": {
      "solar": {
        "time": "1778970016",
        "unit": "W/m²",
        "value": "0.0"
      },
      "uvi": {
        "time": "1778970016",
        "unit": "",
        "value": "0"
      }
    },
    "rainfall": {
      "rain_rate": {
        "time": "1778970016",
        "unit": "mm/hr",
        "value": 0
      },
      "daily": {
        "time": "1778970016",
        "unit": "mm",
        "value": 0.8
      },
      "event": {
        "time": "1778970016",
        "unit": "mm",
        "value": 0.3
      },
      "1_hour": {
        "time": "1778970016",
        "unit": "mm",
        "value": 0
      },
      "weekly": {
        "time": "1778970016",
        "unit": "mm",
        "value": 0.8
      },
      "monthly": {
        "time": "1778970016",
        "unit": "mm",
        "value": 15.5
      },
      "yearly": {
        "time": "1778970016",
        "unit": "mm",
        "value": 115.6
      }
    },
    "wind": {
      "wind_speed": {
        "time": "1778970016",
        "unit": "km/h",
        "value": "13.3"
      },
      "wind_gust": {
        "time": "1778970016",
        "unit": "km/h",
        "value": "14.8"
      },
      "wind_direction": {
        "time": "1778970016",
        "unit": "º",
        "value": "186"
      }
    },
    "pressure": {
      "relative": {
        "time": "1778970016",
        "unit": "hPa",
        "value": "1017.8"
      },
      "absolute": {
        "time": "1778970016",
        "unit": "hPa",
        "value": "1012.7"
      }
    }
  }
}
