{
  "code": 0,
  "msg": "success",
  "time": "1779656719",
  "data": {
    "outdoor": {
      "temperature": {
        "time": "1779656686",
        "unit": "℃",
        "value": "12.7"
      },
      "feels_like": {
        "time": "1779656686",
        "unit": "℃",
        "value": "12.7"
      },
      "app_temp": {
        "time": "1779656686",
        "unit": "℃",
        "value": "11.7"
      },
      "dew_point": {
        "time": "1779656686",
        "unit": "℃",
        "value": "9.0"
      },
      "humidity": {
        "time": "1779656686",
        "unit": "%",
        "value": "78"
      }
    },
    "solar_and_uvi": {
      "solar": {
        "time": "1779656686",
        "unit": "W/m²",
        "value": "2.3"
      },
      "uvi": {
        "time": "1779656686",
        "unit": "",
        "value": "0"
      }
    },
    "rainfall": {
      "rain_rate": {
        "time": "1779656686",
        "unit": "mm/hr",
        "value": 0
      },
      "daily": {
        "time": "1779656686",
        "unit": "mm",
        "value": 0
      },
      "event": {
        "time": "1779656686",
        "unit": "mm",
        "value": 0
      },
      "1_hour": {
        "time": "1779656686",
        "unit": "mm",
        "value": 0
      },
      "weekly": {
        "time": "1779656686",
        "unit": "mm",
        "value": 0
      },
      "monthly": {
        "time": "1779656686",
        "unit": "mm",
        "value": 16.8
      },
      "yearly": {
        "time": "1779656686",
        "unit": "mm",
        "value": 116.8
      }
    },
    "wind": {
      "wind_speed": {
        "time": "1779656686",
        "unit": "km/h",
        "value": "4.0"
      },
      "wind_gust": {
        "time": "1779656686",
        "unit": "km/h",
        "value": "7.2"
      },
      "wind_direction": {
        "time": "1779656686",
        "unit": "º",
        "value": "42"
      }
    },
    "pressure": {
      "relative": {
        "time": "1779656686",
        "unit": "hPa",
        "value": "1017.0"
      },
      "absolute": {
        "time": "1779656686",
        "unit": "hPa",
        "value": "1011.9"
      }
    }
  }
}
