{
  "code": 0,
  "msg": "success",
  "time": "1783212332",
  "data": {
    "outdoor": {
      "temperature": {
        "time": "1783212328",
        "unit": "℃",
        "value": "6.9"
      },
      "feels_like": {
        "time": "1783212328",
        "unit": "℃",
        "value": "5.6"
      },
      "app_temp": {
        "time": "1783212328",
        "unit": "℃",
        "value": "3.8"
      },
      "dew_point": {
        "time": "1783212328",
        "unit": "℃",
        "value": "1.8"
      },
      "humidity": {
        "time": "1783212328",
        "unit": "%",
        "value": "70"
      }
    },
    "solar_and_uvi": {
      "solar": {
        "time": "1783212328",
        "unit": "W/m²",
        "value": "0.0"
      },
      "uvi": {
        "time": "1783212328",
        "unit": "",
        "value": "0"
      }
    },
    "rainfall": {
      "rain_rate": {
        "time": "1783212328",
        "unit": "mm/hr",
        "value": 0
      },
      "daily": {
        "time": "1783212328",
        "unit": "mm",
        "value": 0
      },
      "event": {
        "time": "1783212328",
        "unit": "mm",
        "value": 0
      },
      "1_hour": {
        "time": "1783212328",
        "unit": "mm",
        "value": 0
      },
      "weekly": {
        "time": "1783212328",
        "unit": "mm",
        "value": 0
      },
      "monthly": {
        "time": "1783212328",
        "unit": "mm",
        "value": 0
      },
      "yearly": {
        "time": "1783212328",
        "unit": "mm",
        "value": 159.5
      }
    },
    "wind": {
      "wind_speed": {
        "time": "1783212328",
        "unit": "km/h",
        "value": "7.2"
      },
      "wind_gust": {
        "time": "1783212328",
        "unit": "km/h",
        "value": "7.2"
      },
      "wind_direction": {
        "time": "1783212328",
        "unit": "º",
        "value": "108"
      }
    },
    "pressure": {
      "relative": {
        "time": "1783212328",
        "unit": "hPa",
        "value": "1022.7"
      },
      "absolute": {
        "time": "1783212328",
        "unit": "hPa",
        "value": "1017.6"
      }
    }
  }
}
