{
  "code": 0,
  "msg": "success",
  "time": "1781883049",
  "data": {
    "outdoor": {
      "temperature": {
        "time": "1781883040",
        "unit": "℃",
        "value": "13.5"
      },
      "feels_like": {
        "time": "1781883040",
        "unit": "℃",
        "value": "13.5"
      },
      "app_temp": {
        "time": "1781883040",
        "unit": "℃",
        "value": "10.9"
      },
      "dew_point": {
        "time": "1781883040",
        "unit": "℃",
        "value": "6.4"
      },
      "humidity": {
        "time": "1781883040",
        "unit": "%",
        "value": "62"
      }
    },
    "solar_and_uvi": {
      "solar": {
        "time": "1781883040",
        "unit": "W/m²",
        "value": "383.4"
      },
      "uvi": {
        "time": "1781883040",
        "unit": "",
        "value": "3"
      }
    },
    "rainfall": {
      "rain_rate": {
        "time": "1781883040",
        "unit": "mm/hr",
        "value": 0
      },
      "daily": {
        "time": "1781883040",
        "unit": "mm",
        "value": 0.3
      },
      "event": {
        "time": "1781883040",
        "unit": "mm",
        "value": 12.7
      },
      "1_hour": {
        "time": "1781883040",
        "unit": "mm",
        "value": 0
      },
      "weekly": {
        "time": "1781883040",
        "unit": "mm",
        "value": 13
      },
      "monthly": {
        "time": "1781883040",
        "unit": "mm",
        "value": 42.2
      },
      "yearly": {
        "time": "1781883040",
        "unit": "mm",
        "value": 159.5
      }
    },
    "wind": {
      "wind_speed": {
        "time": "1781883040",
        "unit": "km/h",
        "value": "9.0"
      },
      "wind_gust": {
        "time": "1781883040",
        "unit": "km/h",
        "value": "11.2"
      },
      "wind_direction": {
        "time": "1781883040",
        "unit": "º",
        "value": "271"
      }
    },
    "pressure": {
      "relative": {
        "time": "1781883040",
        "unit": "hPa",
        "value": "1017.6"
      },
      "absolute": {
        "time": "1781883040",
        "unit": "hPa",
        "value": "1012.5"
      }
    }
  }
}
