{
  "code": 0,
  "msg": "success",
  "time": "1781873435",
  "data": {
    "outdoor": {
      "temperature": {
        "time": "1781873380",
        "unit": "℃",
        "value": "7.1"
      },
      "feels_like": {
        "time": "1781873380",
        "unit": "℃",
        "value": "7.1"
      },
      "app_temp": {
        "time": "1781873380",
        "unit": "℃",
        "value": "5.6"
      },
      "dew_point": {
        "time": "1781873380",
        "unit": "℃",
        "value": "4.9"
      },
      "humidity": {
        "time": "1781873380",
        "unit": "%",
        "value": "86"
      }
    },
    "solar_and_uvi": {
      "solar": {
        "time": "1781873380",
        "unit": "W/m²",
        "value": "157.6"
      },
      "uvi": {
        "time": "1781873380",
        "unit": "",
        "value": "1"
      }
    },
    "rainfall": {
      "rain_rate": {
        "time": "1781873380",
        "unit": "mm/hr",
        "value": 0
      },
      "daily": {
        "time": "1781873380",
        "unit": "mm",
        "value": 0.3
      },
      "event": {
        "time": "1781873380",
        "unit": "mm",
        "value": 12.7
      },
      "1_hour": {
        "time": "1781873380",
        "unit": "mm",
        "value": 0
      },
      "weekly": {
        "time": "1781873380",
        "unit": "mm",
        "value": 13
      },
      "monthly": {
        "time": "1781873380",
        "unit": "mm",
        "value": 42.2
      },
      "yearly": {
        "time": "1781873380",
        "unit": "mm",
        "value": 159.5
      }
    },
    "wind": {
      "wind_speed": {
        "time": "1781873380",
        "unit": "km/h",
        "value": "1.8"
      },
      "wind_gust": {
        "time": "1781873380",
        "unit": "km/h",
        "value": "1.8"
      },
      "wind_direction": {
        "time": "1781873380",
        "unit": "º",
        "value": "248"
      }
    },
    "pressure": {
      "relative": {
        "time": "1781873380",
        "unit": "hPa",
        "value": "1017.3"
      },
      "absolute": {
        "time": "1781873380",
        "unit": "hPa",
        "value": "1012.2"
      }
    }
  }
}
